{
  "modules": [
    {
      "name": "TheonaUI2",
      "contentEntries": [
        {
          "path": "file://$PROJECT_DIR$",
          "sourceFolders": []
        }
      ],
      "orderEntries": [
        {
          "name": "Embedded JDK",
          "type": "SDK"
        },
        {
          "name": "<Module source>",
          "type": "Own sources"
        }
      ]
    },
    {
      "name": "TheonaUI2.app",
      "contentEntries": [
        {
          "path": "file://$PROJECT_DIR$/app",
          "sourceFolders": []
        }
      ],
      "orderEntries": [
        {
          "name": "Embedded JDK",
          "type": "SDK"
        },
        {
          "name": "<Module source>",
          "type": "Own sources"
        }
      ]
    }
  ]
}